markets/__init__.py
markets/funcs.py
markets/model.py
markets/data/__init__.py
markets/data/cryptoIndex.csv
markets/data/loader.py
markets-0.0.1.dist-info/LICENSE
markets-0.0.1.dist-info/METADATA
markets-0.0.1.dist-info/WHEEL
markets-0.0.1.dist-info/top_level.txt
markets-0.0.1.dist-info/RECORD
