Metadata-Version: 2.1
Name: markets
Version: 0.0.1
Summary: Tools for analysis of markets.
Home-page: https://github.com/andrea-ci/markets
Author: Andrea Capitanelli
Author-email: andrea.capitanelli@gmail.com
Maintainer: Andrea Capitanelli
Maintainer-email: andrea.capitanelli@gmail.com
License: MIT
Keywords: financial markets analysis statistics
Platform: UNKNOWN
Classifier: Development Status :: 4 - Beta
Classifier: License :: OSI Approved :: MIT License
Classifier: Operating System :: POSIX :: Linux
Classifier: Programming Language :: Python :: 3
Classifier: Topic :: Scientific/Engineering
Requires-Python: >=3.7.0
Requires-Dist: numpy
Requires-Dist: scipy
Requires-Dist: tqdm
